{
  "updatedAt": "2026-07-17T04:14:27.169Z",
  "source": "live",
  "keywords": [
    {
      "keyword": "mlb",
      "traffic": "1000+",
      "blogTotal": 762017,
      "newsTotal": 576676,
      "recentToday": 100,
      "recentWeek": 100,
      "topBlogs": [
        {
          "title": "메이저리그 (MLB) 홈런더비! 2002년생 조던 워커, 역대급...",
          "link": "https://blog.naver.com/kjae1214/224346539315",
          "blogger": "엘라스티걸야구이야기",
          "date": "2026-07-14"
        },
        {
          "title": "1위 경쟁팀과 MLB 복귀를 동시에 노린 승부수. 꽤 무섭습니다",
          "link": "https://blog.naver.com/rlfehdud/224344074298",
          "blogger": "두 아들 아빠의 아마추어 선수 도전기",
          "date": "2026-07-12"
        },
        {
          "title": "이정후 MLB 생존기, 시즌초반 부진탈출 달라진 헬멧이 문제였나?",
          "link": "https://blog.naver.com/july7th73/224328429362",
          "blogger": "수연아빠의 야구장 출동 (개포맘모스)",
          "date": "2026-06-26"
        },
        {
          "title": "MLB 역사상 첫 여성 심판 ‘젠 파월’ 편파 판정의 논란의 심판!!!",
          "link": "https://blog.naver.com/love01th/224346231421",
          "blogger": "ElonMusk_Tesla",
          "date": "2026-07-14"
        },
        {
          "title": "MLB침공 고교야구유망주 수집, 남을까 떠날까",
          "link": "https://blog.naver.com/eos333/224324987563",
          "blogger": "사진가이영학 '고교야구메모리'",
          "date": "2026-06-23"
        }
      ],
      "topNews": [
        {
          "title": "'와 1556억 초대박!' 11승 에이스 번스, 신시내티와 7년 장기 계약…\"구...",
          "link": "https://www.xportsnews.com/article/2173193",
          "press": "",
          "date": "2026-07-17"
        },
        {
          "title": "이대로 325억 사라지나, 복귀하자마자 팔꿈치 잡았다…\"현실 받아들이기...",
          "link": "https://www.mydaily.co.kr/page/view/2026071711341041480",
          "press": "",
          "date": "2026-07-17"
        },
        {
          "title": "MLB·WBC 경험 겸비 이구치, 日 사무라이 재팬 지휘 유력",
          "link": "https://www.topstarnews.net/news/articleView.html?idxno=16137542",
          "press": "",
          "date": "2026-07-17"
        },
        {
          "title": "일본 야구대표팀 차기 감독에 MLB서 뛴 이구치 유력",
          "link": "https://www.yna.co.kr/view/AKR20260717032800007?input=1195m",
          "press": "",
          "date": "2026-07-17"
        },
        {
          "title": "2027시즌 MLB, 3월 24일 역대 가장 이른 개막…노사협상은 변수(종합)",
          "link": "https://www.yna.co.kr/view/AKR20260717020451007?input=1195m",
          "press": "",
          "date": "2026-07-17"
        }
      ],
      "rank": 1
    },
    {
      "keyword": "메가박스",
      "traffic": "200+",
      "blogTotal": 946128,
      "newsTotal": 533594,
      "recentToday": 100,
      "recentWeek": 100,
      "topBlogs": [
        {
          "title": "6천원 할인권 이용해서 HOPE 개봉날 바로보기 (메가박스 방법)",
          "link": "https://blog.naver.com/brandnew9021/224347475619",
          "blogger": "콩콩이네 육아일상❤️",
          "date": "2026-07-15"
        },
        {
          "title": "영화 '날씨의 아이' 재개봉, 메가박스 홍대 아니메 앵콜 상영 및...",
          "link": "https://blog.naver.com/stmisn/224347701429",
          "blogger": "테플로의 영화 이야기",
          "date": "2026-07-15"
        },
        {
          "title": "영화 호프 후기 송도 메가박스 돌비시네마 자리 추천",
          "link": "https://blog.naver.com/alpano/224348888965",
          "blogger": "와이담의 움직이는 하루",
          "date": "2026-07-16"
        },
        {
          "title": "속편 메가박스 코엑스 리클라이너8관 E열 좌석 평일 저녁...",
          "link": "https://blog.naver.com/wmk1003/224348109995",
          "blogger": "삼남매엄마 우밍네 5인가족 일기♡",
          "date": "2026-07-16"
        },
        {
          "title": "쁘띠 쿠키 있음 + 메가박스 얼리버드 포스터 · 오리지널 티켓",
          "link": "https://blog.naver.com/opiate/224347990273",
          "blogger": "소르벳과 오즈마",
          "date": "2026-07-16"
        }
      ],
      "topNews": [
        {
          "title": "JTBC \"'아는 형님' 내일(18일) 결방\"…회생 아닌 \"월드컵 때문\"",
          "link": "https://www.mydaily.co.kr/page/view/2026071713014314591",
          "press": "",
          "date": "2026-07-17"
        },
        {
          "title": "나홍진 '호프', 개봉 3일 만에 100만 돌파…관객 평점·쿠키 유무?",
          "link": "https://www.topstarnews.net/news/articleView.html?idxno=16137541",
          "press": "",
          "date": "2026-07-17"
        },
        {
          "title": "꼬꼬마 최강 10번타자 모여라! ‘강승호·김정우 사인회’ 두산, ‘7월 ...",
          "link": "https://www.sportsseoul.com/news/read/1623020?ref=naver",
          "press": "",
          "date": "2026-07-17"
        },
        {
          "title": "'강승호-김정우 팬사인회' 두산, 25일 ‘7월 두린이날’ 이벤트 진행",
          "link": "http://www.osen.co.kr/article/G1112841207",
          "press": "",
          "date": "2026-07-17"
        },
        {
          "title": "서울국제여성영화제, 국제경쟁 '발견' 본선 8편 발표…역대 최다 출품",
          "link": "https://www.ajunews.com/view/20260715172642845",
          "press": "",
          "date": "2026-07-17"
        }
      ],
      "rank": 2
    },
    {
      "keyword": "웨이브",
      "traffic": "200+",
      "blogTotal": 3353694,
      "newsTotal": 535516,
      "recentToday": 100,
      "recentWeek": 100,
      "topBlogs": [
        {
          "title": "시흥 거북섬 호텔 웨이브엠 이스트 일몰 오션뷰 수영장 조식",
          "link": "https://blog.naver.com/104204303/224320863116",
          "blogger": "very goooood luck",
          "date": "2026-06-19"
        },
        {
          "title": "소프웨이브 리프팅 2달 내돈내받 빡침 후기",
          "link": "https://blog.naver.com/ideanote08/224296725699",
          "blogger": "천사의 알",
          "date": "2026-05-26"
        },
        {
          "title": "포항 풀빌라 독채 펜션 휴양지 감성 오션뷰 벨라웨이브",
          "link": "https://blog.naver.com/starkimpt/224349184643",
          "blogger": "유니크한 나의 하루",
          "date": "2026-07-17"
        },
        {
          "title": "청담동 피부과 소프웨이브 효과 좋아서 또 받은 후기와 가격",
          "link": "https://blog.naver.com/aura_m/224333010797",
          "blogger": "남성 뷰티&패션 블로그 | 아우라M - www.aura-m.net",
          "date": "2026-07-01"
        },
        {
          "title": "동대문피부과 소프웨이브의 오해와 진실",
          "link": "https://blog.naver.com/donalds77/224344874627",
          "blogger": "닥터스피부과 동대문점",
          "date": "2026-07-13"
        }
      ],
      "topNews": [
        {
          "title": "\"협업 제품 어때요?\"... 패션업계 여름 틈새 공략 '후끈' [최기자의 패션...",
          "link": "https://www.meconomynews.com/news/articleView.html?idxno=132892",
          "press": "",
          "date": "2026-07-17"
        },
        {
          "title": "[가요소식] 브브걸, 신나는 서머송 '보디 웨이브'로 컴백",
          "link": "https://www.yna.co.kr/view/AKR20260717030900005?input=1195m",
          "press": "",
          "date": "2026-07-17"
        },
        {
          "title": "브브걸, 남다른 건강美 발산…청량 뭄바톤 ‘BODY WAVE’",
          "link": "https://sports.donga.com/ent/article/all/20260717/134316265/1",
          "press": "",
          "date": "2026-07-17"
        },
        {
          "title": "광화문광장에 해변이 펼쳐진다…도심 속 피서지 '서울썸머비치' 20일 개...",
          "link": "https://www.ajunews.com/view/20260715174419881",
          "press": "",
          "date": "2026-07-17"
        },
        {
          "title": "축제를 한 눈에! 이번 주(07.17.~07.23.) 축제 일정 '서울/경기 및 인천'...",
          "link": "http://www.sisunnews.co.kr/news/articleView.html?idxno=242358",
          "press": "",
          "date": "2026-07-17"
        }
      ],
      "rank": 3
    },
    {
      "keyword": "로봇",
      "traffic": "1000+",
      "blogTotal": 5514145,
      "newsTotal": 2334358,
      "recentToday": 100,
      "recentWeek": 100,
      "topBlogs": [
        {
          "title": "물걸레 로봇청소기 추천 에코백스 X8 올인원 효녀 로청",
          "link": "https://blog.naver.com/jini4998/224348556935",
          "blogger": "끌림",
          "date": "2026-07-16"
        },
        {
          "title": "로보락 가성비 로봇청소기 S8 Pro+ 선택 만족 후기",
          "link": "https://blog.naver.com/hbaroong/224318815708",
          "blogger": "효바룽의 리빙에세이♥",
          "date": "2026-06-17"
        },
        {
          "title": "로보락 로봇청소기 추천 Saros Z70 후기",
          "link": "https://blog.naver.com/smallview/224284417811",
          "blogger": "어디갓츄의 IT스토리",
          "date": "2026-05-13"
        },
        {
          "title": "드리미 로봇청소기 L10s L30s L40s 비교 분석, 세 달...",
          "link": "https://blog.naver.com/record_our/224326246278",
          "blogger": "글쓰는 제인의 N잡 이야기",
          "date": "2026-06-24"
        },
        {
          "title": "다이슨 스팟앤스크럽 로봇 청소기 물 청소 실시간 세척 후기...",
          "link": "https://blog.naver.com/cyh_0919/224349196081",
          "blogger": "오늘의 탠저린",
          "date": "2026-07-17"
        }
      ],
      "topNews": [
        {
          "title": "中 ‘AI 굴기’ 총출동…1100개사·3000개 제품 상하이에 모였다",
          "link": "https://www.kbmaeil.com/article/20260717500090",
          "press": "",
          "date": "2026-07-17"
        },
        {
          "title": "엔비디아, 4B 규모 월드 모델 '코스모스 3 엣지' 공개...'온디바이스 피...",
          "link": "https://www.aitimes.com/news/articleView.html?idxno=212880",
          "press": "",
          "date": "2026-07-17"
        },
        {
          "title": "상하이서 '세계인공지능대회' 개막…中 AI·로봇 성과 한자리에(종합)",
          "link": "https://www.yna.co.kr/view/AKR20260716209051089?input=1195m",
          "press": "",
          "date": "2026-07-17"
        },
        {
          "title": "기업인 900명 만난 조정식 국회의장...제주서 ‘경제계 밀착’ 광폭 행...",
          "link": "https://www.sedaily.com/article/20068841?ref=naver",
          "press": "",
          "date": "2026-07-17"
        },
        {
          "title": "[인사] 부산시",
          "link": "http://www.econonews.co.kr/news/articleView.html?idxno=441354",
          "press": "",
          "date": "2026-07-17"
        }
      ],
      "rank": 4
    },
    {
      "keyword": "미니언즈 몬스터즈",
      "traffic": "100+",
      "blogTotal": 1335,
      "newsTotal": 381,
      "recentToday": 40,
      "recentWeek": 100,
      "topBlogs": [
        {
          "title": "미니언즈 몬스터즈 후기 더빙 쿠키 CGV 특전 평점 굿즈 ott...",
          "link": "https://blog.naver.com/dongi0508/224347613032",
          "blogger": "Der Sinn des Lebens",
          "date": "2026-07-15"
        },
        {
          "title": "기대만땅 미니언즈 앤 몬스터즈 조건없는 웃음으로 스트레스...",
          "link": "https://blog.naver.com/starboa17/224347975748",
          "blogger": "몰쉬미 블로그",
          "date": "2026-07-16"
        },
        {
          "title": "미니언즈 & 몬스터즈 4DX 포스터, TTT",
          "link": "https://blog.naver.com/kim500tae9/224349195923",
          "blogger": "콘체르탄테",
          "date": "2026-07-17"
        },
        {
          "title": "미니언즈&몬스터즈 영화 볼 때 먹기 좋은 만전김X미니언즈...",
          "link": "https://blog.naver.com/manjun_seaweed_korea/224347150243",
          "blogger": "만전김",
          "date": "2026-07-16"
        },
        {
          "title": "영화 미니언즈 몬스터즈 줄거리 결말 쿠키 여러개 단독 시리즈...",
          "link": "https://blog.naver.com/realnogun/224348195242",
          "blogger": "183흔남 노군의 싱글라이프",
          "date": "2026-07-16"
        }
      ],
      "topNews": [
        {
          "title": "나홍진 '호프', 개봉 3일 만에 100만 돌파…관객 평점·쿠키 유무?",
          "link": "https://www.topstarnews.net/news/articleView.html?idxno=16137541",
          "press": "",
          "date": "2026-07-17"
        },
        {
          "title": "[NC박스오피스] '호프' 하루 27만, 압도적 1위...주말 100만 돌파 '조짐'",
          "link": "https://www.nc.press/news/articleView.html?idxno=621041",
          "press": "",
          "date": "2026-07-17"
        },
        {
          "title": "‘호프’ 예매율 55.3% 압도적 1위…‘연휴 특수’로 100만 넘는다",
          "link": "https://www.sportsworldi.com/newsView/20260717507533",
          "press": "",
          "date": "2026-07-17"
        },
        {
          "title": "적수 없는 ‘호프’, 개봉 이틀 만에 60만 돌파",
          "link": "https://www.ichannela.com/news/main/news_detailPage.do?publishId=000000540247",
          "press": "",
          "date": "2026-07-17"
        },
        {
          "title": "3위 조인성·2위 구교환…영화배우 브랜드평판 1위 차지한 '50대 배우'",
          "link": "https://www.wikitree.co.kr/articles/1146972",
          "press": "",
          "date": "2026-07-17"
        }
      ],
      "rank": 5
    },
    {
      "keyword": "박승규",
      "traffic": "100+",
      "blogTotal": 13854,
      "newsTotal": 19833,
      "recentToday": 19,
      "recentWeek": 100,
      "topBlogs": [
        {
          "title": "삼성 박승규 김선우 웨딩사진 속 예비신부 정체는?",
          "link": "https://blog.naver.com/lhswind2/224348288777",
          "blogger": "우수아빠의 인생은",
          "date": "2026-07-16"
        },
        {
          "title": "\"같은 운동선수라 버텼다\" 박승규 예비신부가 밝힌 야구 못하던...",
          "link": "https://blog.naver.com/420yskkk/224349294952",
          "blogger": "소소한일상 그리고 소소한운동",
          "date": "2026-07-17"
        },
        {
          "title": "사이클링 포기한 '박승규'! 부상 '김성윤' 대체자 될까?",
          "link": "https://blog.naver.com/chaesports/224248602349",
          "blogger": "채씨가 전하는 스포츠⚡",
          "date": "2026-04-11"
        },
        {
          "title": "삼성 박승규 5월 최고 수비, 9회 2사 2루에서 왜 모두가 소름...",
          "link": "https://blog.naver.com/rlfehdud/224307489962",
          "blogger": "두 아들 아빠의 아마추어 선수 도전기",
          "date": "2026-06-06"
        },
        {
          "title": "9홈런 커리어하이보다 더 감동적인 '박승규♥예비신부의 이야기'",
          "link": "https://blog.naver.com/dyts60/224349145854",
          "blogger": "크보한입",
          "date": "2026-07-17"
        }
      ],
      "topNews": [
        {
          "title": "'딱 1아웃 더 잡겠다는데' 롯데 에이스, 갑자기 옵션에 미친 사람 됐다...",
          "link": "https://www.xportsnews.com/article/2173180",
          "press": "",
          "date": "2026-07-17"
        },
        {
          "title": "\"옵션 때문인 것 같다\" 진짜 그랬을까? 사실확인 되지 않은 충격적 발언...",
          "link": "https://www.spotvnews.co.kr/news/articleView.html?idxno=828918",
          "press": "",
          "date": "2026-07-16"
        },
        {
          "title": "\"같은 운동선수라 버틸 수 있었다\"…'박승규♥' 예비신부, 결혼 발표 후...",
          "link": "http://www.osen.co.kr/article/G1112840687",
          "press": "",
          "date": "2026-07-16"
        },
        {
          "title": "수차례 내저은 고개, 롯데 156km 에이스 교체거부…옵션 때문? 그만큼 컸...",
          "link": "https://www.spotvnews.co.kr/news/articleView.html?idxno=828905",
          "press": "",
          "date": "2026-07-16"
        },
        {
          "title": "기분좋게 후반기 시작했다!…‘김영웅 쐐기포+양창섭 8승’ 삼성, 후반...",
          "link": "https://www.mk.co.kr/article/12100746",
          "press": "",
          "date": "2026-07-16"
        }
      ],
      "rank": 6
    },
    {
      "keyword": "뉴스파이터",
      "traffic": "200+",
      "blogTotal": 39828,
      "newsTotal": 76090,
      "recentToday": 12,
      "recentWeek": 100,
      "topBlogs": [
        {
          "title": "뉴스파이터 김명준 MBN퇴사 후 프리랜서 선언",
          "link": "https://blog.naver.com/lmw2625/224266868437",
          "blogger": "FeatherAs",
          "date": "2026-04-27"
        },
        {
          "title": "뉴스파이터 무명전설 출연!성리 하루 ...",
          "link": "https://blog.naver.com/tanhi/224282288666",
          "blogger": "더한 행복, 준비된 향기",
          "date": "2026-05-11"
        },
        {
          "title": "하도 먹어 내성 생긴 상태\"...전 매니저, 추가 폭로  [뉴스파이터]",
          "link": "https://blog.naver.com/plug_and_play_life/224119389976",
          "blogger": "Plug & Play Life (플러그 앤 플레이 라이프)",
          "date": "2025-12-23"
        },
        {
          "title": "MBN 뉴스파이터 김명준 하차 이유 후임 누구? 휴가 아닌 앵커...",
          "link": "https://blog.naver.com/shyhjin/224181452034",
          "blogger": "진매료의 핫플레이스 : )",
          "date": "2026-02-12"
        },
        {
          "title": "김명준 8년 만에 뉴스파이터 하차 이유는 성추행 관련...",
          "link": "https://blog.naver.com/pang_gom/224181285297",
          "blogger": "미디어 부수기!!",
          "date": "2026-02-12"
        }
      ],
      "topNews": [
        {
          "title": "[총수家] 젠슨 황 엔비디아 CEO ②ㅣ 글로벌 AI 생태계 확장…일본과 협...",
          "link": "https://www.cbci.co.kr/news/articleView.html?idxno=589785",
          "press": "",
          "date": "2026-07-17"
        },
        {
          "title": "\"아들에게 맞았다\"는 아버지와 억울한 아들? 재판 중 밝혀진 '충격적 진...",
          "link": "http://www.mbn.co.kr/pages/news/newsView.php?news_seq_no=5206468",
          "press": "",
          "date": "2026-07-16"
        },
        {
          "title": "탁구 치다 '쿵'…심정지로 쓰러진 남성, 옆 코트 비번 경찰이 살렸다 - ...",
          "link": "http://www.mbn.co.kr/pages/news/newsView.php?news_seq_no=5206467",
          "press": "",
          "date": "2026-07-16"
        },
        {
          "title": "'테러 자작극' 정이한, 결국 수갑 찬 채 구속 송치 - 뉴스파이터",
          "link": "http://www.mbn.co.kr/pages/news/newsView.php?news_seq_no=5206465",
          "press": "",
          "date": "2026-07-16"
        },
        {
          "title": "\"개인 사정\"…'중학생 성매매' 청주시의원 최영중, 결국 사퇴 - 뉴스파이...",
          "link": "http://www.mbn.co.kr/pages/news/newsView.php?news_seq_no=5206464",
          "press": "",
          "date": "2026-07-16"
        }
      ],
      "rank": 7
    },
    {
      "keyword": "송성문",
      "traffic": "1000+",
      "blogTotal": 26688,
      "newsTotal": 46817,
      "recentToday": 10,
      "recentWeek": 100,
      "topBlogs": [
        {
          "title": "샌디에이고 팬들은 왜 송성문에게 분노했을까? 타티스 송구...",
          "link": "https://blog.naver.com/rlfehdud/224291785592",
          "blogger": "두 아들 아빠의 아마추어 선수 도전기",
          "date": "2026-05-21"
        },
        {
          "title": "송성문의 ABS 챌린지를 묵살한 주심은 젠 파월, MLB의 ABS...",
          "link": "https://blog.naver.com/caleb0901/224345567166",
          "blogger": "이과장의 스포츠",
          "date": "2026-07-13"
        },
        {
          "title": "심판 억까에 타격코치는 퇴장까지 송성문 챌린지 거부 사태",
          "link": "https://blog.naver.com/420yskkk/224345094472",
          "blogger": "소소한일상 그리고 소소한운동",
          "date": "2026-07-13"
        },
        {
          "title": "MLB 무대 적응 마친 송성문, 샌디에이고를 위한 첫 홈런포 가동",
          "link": "https://blog.naver.com/ft-times/224333979749",
          "blogger": "FT스포츠",
          "date": "2026-07-02"
        },
        {
          "title": "[MLB] \"225억 슈퍼 유틸리티 송성문\" 샌디에이고 감독도...",
          "link": "https://blog.naver.com/rgw1019/224344350025",
          "blogger": "낭만야구",
          "date": "2026-07-12"
        }
      ],
      "topNews": [
        {
          "title": "2027시즌 MLB, 3월 24일 역대 가장 이른 개막…노사협상은 변수(종합)",
          "link": "https://www.yna.co.kr/view/AKR20260717020451007?input=1195m",
          "press": "",
          "date": "2026-07-17"
        },
        {
          "title": "'전 롯데' 레일리, 통산 100홀드까지 '-7'…MLB 후반기 재개",
          "link": "https://www.news1.kr/sports/overseas-baseball/6231247",
          "press": "",
          "date": "2026-07-17"
        },
        {
          "title": "2027 MLB, 봄보다 빠른 개막 선언..'직장폐쇄' 가능성 남아",
          "link": "https://www.stnsports.co.kr/news/articleView.html?idxno=319376",
          "press": "",
          "date": "2026-07-17"
        },
        {
          "title": "2027시즌 MLB, 역대 가장 이른 3월 24일 개막 발표… 노사 협상이 변수",
          "link": "https://www.edaily.co.kr/news/newspath.asp?newsid=02604326645515504",
          "press": "",
          "date": "2026-07-17"
        },
        {
          "title": "2027시즌 MLB, 내년 3월 25일 개막…노사 협약 갈등 변수",
          "link": "https://www.news1.kr/sports/overseas-baseball/6231200",
          "press": "",
          "date": "2026-07-17"
        }
      ],
      "rank": 8
    },
    {
      "keyword": "마사회",
      "traffic": "100+",
      "blogTotal": 101584,
      "newsTotal": 213332,
      "recentToday": 8,
      "recentWeek": 100,
      "topBlogs": [
        {
          "title": "3천 원으로 트랙터 마차 타고 제주여행을? 한국마사회 제주목장",
          "link": "https://blog.naver.com/jisunny1215/224325569820",
          "blogger": "룰루랄라의 여행 노트",
          "date": "2026-06-24"
        },
        {
          "title": "한국마사회 자연친화 천연이끼 인테리어 아트월 벽면녹화 시공",
          "link": "https://blog.naver.com/scandia-moss/224346498466",
          "blogger": "스칸디아모스 공식블로그",
          "date": "2026-07-15"
        },
        {
          "title": "1월 제주도 여행 한국마사회 제주목장 동백꽃길과 위미리 3760",
          "link": "https://blog.naver.com/9unique/224116841250",
          "blogger": "유니크의 제주살이",
          "date": "2025-12-20"
        },
        {
          "title": "경마장 이전 본격화! 한국마사회 이전과 과천 부동산 전망 총정리",
          "link": "https://blog.naver.com/nice4263000/224330257375",
          "blogger": "인덕원 지성공인중개사",
          "date": "2026-06-29"
        },
        {
          "title": "“제주, 대한민국 말산업 수도”…마사회와 미래 성장전략 논의",
          "link": "https://blog.naver.com/kingoftheone/224323475733",
          "blogger": "전국뉴스",
          "date": "2026-06-22"
        }
      ],
      "topNews": [
        {
          "title": "방미통위, 유진 YTN 최대주주 직권취소?… 민영화 다시 수면 위",
          "link": "http://www.journalist.or.kr/news/article.html?no=61293",
          "press": "",
          "date": "2026-07-17"
        },
        {
          "title": "림피드, 농식품테크 창업박람회 참가...킨포라·에퀸포라 선보여",
          "link": "https://www.thepowernews.co.kr/view.php?ud=202607171116511669aeda69934_7",
          "press": "",
          "date": "2026-07-17"
        },
        {
          "title": "한국마사회 우희종 회장, '2026 한국의 영향력 있는 CEO' 리더십 경영 분...",
          "link": "https://www.m-i.kr/news/articleView.html?idxno=1392557",
          "press": "",
          "date": "2026-07-17"
        },
        {
          "title": "서울경마 장거리 강자들… 하반기 첫 승부서 '부진 탈출' 노려",
          "link": "https://www.m-i.kr/news/articleView.html?idxno=1392555",
          "press": "",
          "date": "2026-07-17"
        },
        {
          "title": "한국마사회, 인권경영 우수기관 인증 취득",
          "link": "https://www.m-i.kr/news/articleView.html?idxno=1392556",
          "press": "",
          "date": "2026-07-17"
        }
      ],
      "rank": 9
    },
    {
      "keyword": "윌리암 살리바",
      "traffic": "500+",
      "blogTotal": 506,
      "newsTotal": 262,
      "recentToday": 3,
      "recentWeek": 55,
      "topBlogs": [
        {
          "title": "확인합니다: 윌리암 살리바의 뒤를 이어 그리즈만과 레알...",
          "link": "https://blog.naver.com/stockportcountyfc/223798206070",
          "blogger": "GWFC & STO & MUN",
          "date": "2025-03-16"
        },
        {
          "title": "레알 마드리드, '1502억' 윌리암 살리바 영입 추진…역대 최고...",
          "link": "https://blog.naver.com/fewers4578/223771547422",
          "blogger": "토판사 체육관",
          "date": "2025-02-24"
        },
        {
          "title": "윌리암 살리바 OGC 니스로 이적 완료",
          "link": "https://blog.naver.com/sho3603/222200136850",
          "blogger": "삥이N스포츠_Official",
          "date": "2021-01-07"
        },
        {
          "title": "아스날 수비수 ‘윌리암 살리바’, 마르세유로 임대 이적 근접",
          "link": "https://blog.naver.com/iyulje93/222433998935",
          "blogger": "뼈시티의 축구일지",
          "date": "2021-07-16"
        },
        {
          "title": "프랑스 살리바가 일기즈 탄타셰프 주심의 판정을 강하게...",
          "link": "https://blog.naver.com/trendspoiler/224337123352",
          "blogger": "트렌드 스포일러",
          "date": "2026-07-05"
        }
      ],
      "topNews": [
        {
          "title": "'결승 같은 준결승' 스페인, 프랑스 잡고 결승행",
          "link": "https://www.ggilbo.com/news/articleView.html?idxno=1169433",
          "press": "",
          "date": "2026-07-15"
        },
        {
          "title": "'두손 두발 다 들었다' 스페인에 0-2 완패를 '시원하게' 인정한 프랑스...",
          "link": "https://www.sportschosun.com/football/2026-07-15/202607150100093490005853",
          "press": "",
          "date": "2026-07-15"
        },
        {
          "title": "음바페의 프랑스 꺾은 스페인, 16년 만에 결승⋯佛 감독 \"심판은 자격 있...",
          "link": "http://www.inews24.com/view/1985681",
          "press": "",
          "date": "2026-07-15"
        },
        {
          "title": "화려한 축구 프랑스, 견고한 스페인 수비벽 못뚫었다… 라민 야말 영리...",
          "link": "https://www.smartbizn.com/news/articleView.html?idxno=148587",
          "press": "",
          "date": "2026-07-15"
        },
        {
          "title": "프랑스, 월드컵 4강 역사상 최악의 공격력! 음바페 보유국이 이딴 경기...",
          "link": "http://www.footballist.co.kr/news/articleView.html?idxno=212266",
          "press": "",
          "date": "2026-07-15"
        }
      ],
      "rank": 10
    }
  ]
}