{
  "updatedAt": "2026-07-13T20:18:25.180Z",
  "source": "live",
  "keywords": [
    {
      "keyword": "skhy",
      "traffic": "500+",
      "blogTotal": 3405,
      "newsTotal": 591,
      "recentToday": 87,
      "recentWeek": 100,
      "topBlogs": [
        {
          "title": "SK하이닉스 SKHY 미국상장후 전략",
          "link": "https://blog.naver.com/going_tothe_moon/224341419296",
          "blogger": "고잉투더문",
          "date": "2026-07-09"
        },
        {
          "title": "[SK하이닉스 티커] 스페이스X(SPCX)와 SK하이닉스(SKHY)의...",
          "link": "https://blog.naver.com/cpath/224342859005",
          "blogger": "제이콥의 일상 탐구",
          "date": "2026-07-10"
        },
        {
          "title": "나스닥 티커 SKHY(SK하이닉스)로 ADR 거래시작, 최태원회장의...",
          "link": "https://blog.naver.com/sendy71/224343728763",
          "blogger": "지니의 머니로그",
          "date": "2026-07-11"
        },
        {
          "title": "미국서 SK하이닉스 투자 가능해졌다…SKHY·SKHX·SKHZ...",
          "link": "https://blog.naver.com/bluebelldaum/224344089600",
          "blogger": "달팽이처럼 여유롭게",
          "date": "2026-07-12"
        },
        {
          "title": "\"SK하이닉스 ADR\" 미국 나스닥 상장 SKHY 공모규모부터 투자...",
          "link": "https://blog.naver.com/vlich/224341447163",
          "blogger": "유희로그",
          "date": "2026-07-09"
        }
      ],
      "topNews": [
        {
          "title": "SK하이닉스 ADR, 프리마켓서 9% 하락…본주 급락 여파",
          "link": "https://www.newsis.com/view/NISX20260714_0003707701",
          "press": "",
          "date": "2026-07-13"
        },
        {
          "title": "사랑해(S) 김희영(KHY)?...최태원 SNS의 'S KHY' 논란 해프닝",
          "link": "https://www.abcn.kr/news/articleView.html?idxno=89391",
          "press": "",
          "date": "2026-07-13"
        },
        {
          "title": "SK하이닉스 ADR도 본주 따라 급락…AI 과열론에 10%↓",
          "link": "https://news.einfomax.co.kr/news/articleView.html?idxno=4424730",
          "press": "",
          "date": "2026-07-13"
        },
        {
          "title": "[AI MY 뉴스] 뉴욕 반도체주 프리뷰...SK하이닉스 ADR 9%↓·마이크론 5%...",
          "link": "https://www.newspim.com/news/view/20260713001176",
          "press": "",
          "date": "2026-07-13"
        },
        {
          "title": "뉴욕증시 개장 전 특징주, 에너지주·쇼피파이·MGM↑ VS SK하이닉스·메...",
          "link": "https://www.newspim.com/news/view/20260713001175",
          "press": "",
          "date": "2026-07-13"
        }
      ],
      "rank": 1
    },
    {
      "keyword": "참교육",
      "traffic": "10000+",
      "blogTotal": 143309,
      "newsTotal": 53929,
      "recentToday": 60,
      "recentWeek": 100,
      "topBlogs": [
        {
          "title": "서이초 사건 학부모 누구? 참교육 우진 엄마 실제 사건",
          "link": "https://blog.naver.com/gashwoon/224316926434",
          "blogger": "개쉬운영어",
          "date": "2026-06-15"
        },
        {
          "title": "드라마 참교육 후기 | 보기 꺼렸는데 공개 한 달 뒤에 결국...",
          "link": "https://blog.naver.com/gomsolvie/224344448812",
          "blogger": "곰솔이의 영화연애",
          "date": "2026-07-12"
        },
        {
          "title": "참교육 우진엄마 박지연 최강 빌런? 조규철 한예리 민지웅",
          "link": "https://blog.naver.com/above_cloud/224318603210",
          "blogger": "과몰입 공간",
          "date": "2026-06-17"
        },
        {
          "title": "넷플릭스 '참교육' 김무열, 웹툰 캐릭터보다 더 멋진 배우였네요",
          "link": "https://blog.naver.com/ohilkwon3335/224328735919",
          "blogger": "일권네찰매생이",
          "date": "2026-06-27"
        },
        {
          "title": "유퀴즈 참교육 김무열, 윤승아와 판자촌 과거 딛고 이룬...",
          "link": "https://blog.naver.com/zumzany/224333701827",
          "blogger": "점자니의 점잖은 생활",
          "date": "2026-07-02"
        }
      ],
      "topNews": [
        {
          "title": "충남교육청판 ‘참교육’ 시작… ‘교권보호관’ 7월 출범",
          "link": "https://www.seoul.co.kr/news/plan/2026/07/14/20260714022001?wlog_tag3=naver",
          "press": "",
          "date": "2026-07-13"
        },
        {
          "title": "'모범택시' 넘었다…시청률 22% 뚫고 벌써 '시즌2' 얘기 나오는 한국 드...",
          "link": "https://www.wikitree.co.kr/articles/1146094",
          "press": "",
          "date": "2026-07-13"
        },
        {
          "title": "‘힘 커진 경찰’ 시리즈 호평… ‘교실 위기’ 지속적 보도 주문",
          "link": "https://www.kmib.co.kr/article/view.asp?arcid=1783923538&code=13110000&cp=nv",
          "press": "",
          "date": "2026-07-13"
        },
        {
          "title": "[이철희 칼럼]트럼프의 ‘동맹 참교육’",
          "link": "https://www.donga.com/news/Opinion/article/all/20260713/134291825/2",
          "press": "",
          "date": "2026-07-13"
        },
        {
          "title": "[종합] \"혹시 오늘 예능 마지막인가요?\"… '아니 근데 진짜!' 차정원, 반...",
          "link": "https://www.topstarnews.net/news/articleView.html?idxno=16133397",
          "press": "",
          "date": "2026-07-13"
        }
      ],
      "rank": 2
    },
    {
      "keyword": "2002년 fifa 월드컵",
      "traffic": "500+",
      "blogTotal": 9386,
      "newsTotal": 32472,
      "recentToday": 34,
      "recentWeek": 90,
      "topBlogs": [
        {
          "title": "2002년 FIFA 월드컵이 오늘... 북중미 월드컵 4강의 놀라운...",
          "link": "https://blog.naver.com/the_prominence_flame/224345691799",
          "blogger": "희림(熙林)'s 블로그",
          "date": "2026-07-14"
        },
        {
          "title": "2002년 2002 FIFA 월드컵 대회 한국/일본 기념 우표 5종 세트...",
          "link": "https://blog.naver.com/3qu6mvfqz2c/224329197976",
          "blogger": "3qu6mvfqz2c님의 블로그",
          "date": "2026-06-27"
        },
        {
          "title": "2002년 2002 FIFA 월드컵 대회 한국/일본 기념 우표 5종 세트...",
          "link": "https://blog.naver.com/youngsorbet66/224248460910",
          "blogger": "youngsorbet66님의 블로그",
          "date": "2026-04-11"
        },
        {
          "title": "평소 사용용 2002년월드컵우표가격 2002년 2002 FIFA 월드컵...",
          "link": "https://blog.naver.com/ww59ey1o/224301423751",
          "blogger": "ww59ey1o님의 블로그",
          "date": "2026-05-31"
        },
        {
          "title": "한국 조폐공사 2002년 한일 FIFA 월드컵 기념 주화민트의...",
          "link": "https://blog.naver.com/iwzlpx3sv26/224162184263",
          "blogger": "48분전",
          "date": "2026-01-28"
        }
      ],
      "topNews": [
        {
          "title": "14억 중국인 좌절 \"128개국으로 늘려도 힘들 것\"...'64개국 확대' 월드컵...",
          "link": "https://www.spotvnews.co.kr/news/articleView.html?idxno=828312",
          "press": "",
          "date": "2026-07-13"
        },
        {
          "title": "\"홍명보 감독 고마워! 수준 높은 한국대표팀 지도, 엄청난 특권이었어\"...",
          "link": "https://www.xportsnews.com/article/2171651",
          "press": "",
          "date": "2026-07-13"
        },
        {
          "title": "2026 북중미 월드컵 우승의 향배는? 누가 우승컵을 거머쥘 것인가?",
          "link": "https://www.ilemonde.com/news/articleView.html?idxno=30334",
          "press": "",
          "date": "2026-07-13"
        },
        {
          "title": "중국을 위한 계획인가...32개국→48개국→4년 만에 또 64개국 확대? 인판...",
          "link": "https://www.sportschosun.com/football/2026-07-13/202607130100083000005211",
          "press": "",
          "date": "2026-07-13"
        },
        {
          "title": "48개국 모자라 \"64개국 검토\"…'중국도?' 월드컵 복귀하나",
          "link": "https://news.jtbc.co.kr/article/NB12308045?influxDiv=NAVER",
          "press": "",
          "date": "2026-07-13"
        }
      ],
      "rank": 3
    },
    {
      "keyword": "미군",
      "traffic": "2000+",
      "blogTotal": 1451210,
      "newsTotal": 1154995,
      "recentToday": 32,
      "recentWeek": 100,
      "topBlogs": [
        {
          "title": "2026 괌 태교여행 3️ | 이파오비치 스노클링, 남부투어, 미군...",
          "link": "https://blog.naver.com/sg20051119/224332288341",
          "blogger": "positive energy, spread love",
          "date": "2026-06-30"
        },
        {
          "title": "미군 배급 식량인 C Ration의 추억,처음 미제 물건을 접한...",
          "link": "https://blog.naver.com/amapola27/224323692604",
          "blogger": "amapola27님의 블로그",
          "date": "2026-06-22"
        },
        {
          "title": "[시공 후기] 까다로운 미군부대 음향 시스템 완벽 교체!",
          "link": "https://blog.naver.com/visionwave2025/224294728961",
          "blogger": "대구 음향 영상 장비 전문업체 비젼웨이브",
          "date": "2026-05-24"
        },
        {
          "title": "프라운트힐스 평택 미군 렌탈하우스 모델하우스 정보",
          "link": "https://blog.naver.com/lynn_u/224086505512",
          "blogger": "연유의 부동산정보",
          "date": "2025-11-24"
        },
        {
          "title": "평택미군기지감시보고서 260618",
          "link": "https://blog.naver.com/jgmoon11/224329446908",
          "blogger": "똘똘이11의 블로그 JGMoon`s Blog",
          "date": "2026-06-28"
        }
      ],
      "topNews": [
        {
          "title": "트럼프 “이란 대신 美가 ‘호르무즈 수호자’ 될 것... 대가도 받겠다...",
          "link": "https://www.sedaily.com/article/20067293?ref=naver",
          "press": "",
          "date": "2026-07-13"
        },
        {
          "title": "[뉴욕증시-1보] 이란 해역 재봉쇄에 장기전 우려…하락 마감",
          "link": "https://news.einfomax.co.kr/news/articleView.html?idxno=4424739",
          "press": "",
          "date": "2026-07-13"
        },
        {
          "title": "\"이란 남부·남동부에 미사일 떨어져‥폭발음도 들려\"",
          "link": "https://imnews.imbc.com/news/2026/world/article/6837164_36925.html",
          "press": "",
          "date": "2026-07-13"
        },
        {
          "title": "美 이란 재봉쇄에 국제유가 요동…WTI 10% 급등",
          "link": "https://biz.sbs.co.kr/article_hub/20000322278?division=NAVER",
          "press": "",
          "date": "2026-07-13"
        },
        {
          "title": "미군, 이란 공격에 해상드론 첫 투입…\"잠수함·함정시설 타격\"",
          "link": "http://www.yonhapnewstv.co.kr/news/MYH20260714051121w56",
          "press": "",
          "date": "2026-07-13"
        }
      ],
      "rank": 4
    },
    {
      "keyword": "무인 항공기",
      "traffic": "100+",
      "blogTotal": 60207,
      "newsTotal": 99359,
      "recentToday": 22,
      "recentWeek": 100,
      "topBlogs": [
        {
          "title": "한서대 무인항공기학부 편입 , 처음부터 이렇게 준비했어요 !",
          "link": "https://blog.naver.com/rorororooo/224252576016",
          "blogger": "양세마리원단",
          "date": "2026-04-15"
        },
        {
          "title": "하늘 위 작은 비행체를 찾아내는 AI | CCTV 무인항공기 탐지",
          "link": "https://blog.naver.com/hikasiu/224341761596",
          "blogger": "어항에서 만나는 아이디어",
          "date": "2026-07-09"
        },
        {
          "title": "【농업용 드론】ePropelled, 차세대 농업용 무인항공기(UAV)...",
          "link": "https://blog.naver.com/foodrist/224323415744",
          "blogger": "농 업 문 화 원",
          "date": "2026-06-23"
        },
        {
          "title": "무인항공기의 개념과 분류 한눈에 보기",
          "link": "https://blog.naver.com/colorrice/223772787916",
          "blogger": "온누리무인항공",
          "date": "2025-02-25"
        },
        {
          "title": "국내 무인항공기 기술의 주역, 프리뉴 성장 배경과 핵심 역량",
          "link": "https://blog.naver.com/boo817a/224323481774",
          "blogger": "티비리뷰엉",
          "date": "2026-06-22"
        }
      ],
      "topNews": [
        {
          "title": "후티 반군, 사우디 아브하 공항 타격…\"사나 공항 공습 보복\"",
          "link": "https://www.yna.co.kr/view/AKR20260714006700079?input=1195m",
          "press": "",
          "date": "2026-07-13"
        },
        {
          "title": "보령, 오늘부터 드론-항공기로 벼 병해충 방제",
          "link": "https://www.donga.com/news/Society/article/all/20260714/134290601/2",
          "press": "",
          "date": "2026-07-13"
        },
        {
          "title": "[시론] ‘3대 메가프로젝트’ 성공을 위한 군(軍)의 역할과 안보",
          "link": "https://www.dnews.co.kr/uhtml/view.jsp?idxno=202607121352487990823",
          "press": "",
          "date": "2026-07-13"
        },
        {
          "title": "에어로바이런먼트(AVAV), 유럽 군 인증·5억 달러 계약 ‘겹호재’…매...",
          "link": "https://www.tokenpost.kr/news/market/377311",
          "press": "",
          "date": "2026-07-13"
        },
        {
          "title": "고성 밤나무 무인기 항공방제 '효과적'",
          "link": "http://www.gnmaeil.com/news/articleView.html?idxno=590678",
          "press": "",
          "date": "2026-07-13"
        }
      ],
      "rank": 5
    },
    {
      "keyword": "jtbc",
      "traffic": "2000+",
      "blogTotal": 1245381,
      "newsTotal": 2486105,
      "recentToday": 21,
      "recentWeek": 100,
      "topBlogs": [
        {
          "title": "이혼숙려캠프 진실공방부부 남편 두집살림 뻔뻔한 해명 (JTBC...",
          "link": "https://blog.naver.com/euene1111/224341995468",
          "blogger": "보는 사람",
          "date": "2026-07-10"
        },
        {
          "title": "\"JTBC가 또...\" '신입사원 강회장' 최악의 황당결말에 시청자들...",
          "link": "https://blog.naver.com/news_curator_j/224337455693",
          "blogger": "핫 뉴스만 콕 집어요",
          "date": "2026-07-06"
        },
        {
          "title": "김웅 전 의원 \"jTBC 사태와 터널링 의혹...SLL중 문제 개입돼...",
          "link": "https://blog.naver.com/zoomin0313/224339490581",
          "blogger": "'필염산하(筆染山河)'",
          "date": "2026-07-07"
        },
        {
          "title": "앞 살아 돌아온 강용호, 황준현은? 12회 예고 JTBC 토일 드라마",
          "link": "https://blog.naver.com/alsk1130/224336650102",
          "blogger": "차카니의 잡다한 일상과 드라마리뷰",
          "date": "2026-07-05"
        },
        {
          "title": "JTBC 파산 논란, 중앙 그룹 부도와 회생 절차까지 간 이유",
          "link": "https://blog.naver.com/tarames/224322024227",
          "blogger": "한가한 경제 재테크",
          "date": "2026-06-20"
        }
      ],
      "topNews": [
        {
          "title": "“JTBC 2026년 2월 채권발행 당시… 금융사, 자본잠식 상황 숨겨” [경제...",
          "link": "https://www.segye.com/newsView/20260713518451?OutUrl=naver",
          "press": "",
          "date": "2026-07-13"
        },
        {
          "title": "중앙그룹 채권 피해자들 “부실 채권, 경영진 정말 몰랐나”",
          "link": "https://www.donga.com/news/Society/article/all/20260714/134292357/2",
          "press": "",
          "date": "2026-07-13"
        },
        {
          "title": "카리나가 말한 극단 감량, 몸에는 어떤 부담 줄까 [헬스톡]",
          "link": "http://www.fnnews.com/news/202607131931172540",
          "press": "",
          "date": "2026-07-13"
        },
        {
          "title": "'트롯거성' 이찬원, 7월 1주 차 평점랭킹 TOP2...230주 연속 2위",
          "link": "https://www.topstarnews.net/news/articleView.html?idxno=16133435",
          "press": "",
          "date": "2026-07-13"
        },
        {
          "title": "‘아파트’ 임소윤, 본격적인 서사 여는 서무주임 오윤서 역",
          "link": "https://sports.khan.co.kr/article/202607140240003?pt=nv",
          "press": "",
          "date": "2026-07-13"
        }
      ],
      "rank": 6
    },
    {
      "keyword": "수성구",
      "traffic": "100+",
      "blogTotal": 2378418,
      "newsTotal": 353169,
      "recentToday": 0,
      "recentWeek": 100,
      "topBlogs": [
        {
          "title": "수성구피부과 브라질리언 제모 통증 및 가격 내돈내산 후기!",
          "link": "https://blog.naver.com/vanillabean1/224340025816",
          "blogger": "✨BEAUTY✨ KOREA",
          "date": "2026-07-08"
        },
        {
          "title": "범어동 필라테스 기초체력 키우기 좋은 대구 수성구...",
          "link": "https://blog.naver.com/love_hcjh/224344997121",
          "blogger": "별밤쌤 | 유치원 어린이집 교사 자료 저장소",
          "date": "2026-07-13"
        },
        {
          "title": "대구수성구동물병원 본동물메디컬센터24시수성점 고양이 심장...",
          "link": "https://blog.naver.com/pooh3653/224344520566",
          "blogger": "냥이숙려캠프",
          "date": "2026-07-13"
        },
        {
          "title": "수성구보청기 만족스런 선물",
          "link": "https://blog.naver.com/grooverdk/224235922706",
          "blogger": "DK’s 취미생활",
          "date": "2026-03-31"
        },
        {
          "title": "대구 수성구 맛집 베스트 수성아일랜드",
          "link": "https://blog.naver.com/seonah14/224296560653",
          "blogger": "초코홀릭의 블로그",
          "date": "2026-05-26"
        }
      ],
      "topNews": [
        {
          "title": "“동대구역에서 ‘뚜비’ 인형극 관람해 보세요”",
          "link": "https://www.donga.com/news/Society/article/all/20260713/134290730/2",
          "press": "",
          "date": "2026-07-13"
        },
        {
          "title": "‘쾅’ 들이받고 줄행랑친 음주 운전자, 붙잡고 보니…‘반전 신분’에...",
          "link": "https://www.mk.co.kr/article/12097709",
          "press": "",
          "date": "2026-07-13"
        },
        {
          "title": "[2026 대구경북 이노비즈 기업을 찾아서] (9)종합디자인전문기업 ㈜디엔...",
          "link": "https://www.idaegu.co.kr/news/articleView.html?idxno=553743",
          "press": "",
          "date": "2026-07-13"
        },
        {
          "title": "대구 시내 공공형 물놀이장 이번 주 개장",
          "link": "https://www.idaegu.co.kr/news/articleView.html?idxno=553762",
          "press": "",
          "date": "2026-07-13"
        },
        {
          "title": "'폭염 진흥시설' 생활 밀착형으로 확장해야",
          "link": "http://www.ujeil.com/news/articleView.html?idxno=388724",
          "press": "",
          "date": "2026-07-13"
        }
      ],
      "rank": 7
    },
    {
      "keyword": "넷플릭스",
      "traffic": "2000+",
      "blogTotal": 3821654,
      "newsTotal": 968338,
      "recentToday": 0,
      "recentWeek": 100,
      "topBlogs": [
        {
          "title": "넷플릭스 요금제 가격 비교 광고형 스탠다드 프리미엄 차이...",
          "link": "https://blog.naver.com/yo7ung/224331768587",
          "blogger": "낭만테크의 IT 놀이터",
          "date": "2026-06-30"
        },
        {
          "title": "전 세계 1위 \"사탄 들렸어?\" 밈 탄생시킨 넷플릭스 한국드라마",
          "link": "https://blog.naver.com/komartin/224344561291",
          "blogger": "히뎀언니의 오늘",
          "date": "2026-07-13"
        },
        {
          "title": "넷플릭스 한국 영화 공포특급 정보와 리뷰 \"귀신은 91분 뒤에...",
          "link": "https://blog.naver.com/hinesisy/224342151889",
          "blogger": "영화처럼 낭만이 있는 삶",
          "date": "2026-07-10"
        },
        {
          "title": "넷플릭스 요금제 가격 정리 · 프리미엄 4K를 월 5천원대로...",
          "link": "https://blog.naver.com/yjg01212/224341243992",
          "blogger": "IT's ivory",
          "date": "2026-07-09"
        },
        {
          "title": "넷플릭스 프리미엄 요금제 70% 할인 받아 5천원에 구독하는법",
          "link": "https://blog.naver.com/fje0978bb/224335924672",
          "blogger": "정오의게임",
          "date": "2026-07-04"
        }
      ],
      "topNews": [
        {
          "title": "[속보]나스닥, 호르무즈 긴장·유가 급등에 1.6%↓…하이닉스 ADR 9.3%↓(...",
          "link": "https://www.edaily.co.kr/news/newspath.asp?newsid=01744966645514520",
          "press": "",
          "date": "2026-07-13"
        },
        {
          "title": "'모범택시' 넘었다…시청률 22% 뚫고 벌써 '시즌2' 얘기 나오는 한국 드...",
          "link": "https://www.wikitree.co.kr/articles/1146094",
          "press": "",
          "date": "2026-07-13"
        },
        {
          "title": "'CA 노숙자촌' 신고까지…알고 보니 넷플릭스 촬영장",
          "link": "https://www.radiokorea.com/news/article.php?uid=499245",
          "press": "",
          "date": "2026-07-13"
        },
        {
          "title": "'폭싹' 아이유 아역 김태연, 학교서 '인성왕' 상장 받았다 \"잘했어!\"",
          "link": "https://www.xportsnews.com/article/2171884",
          "press": "",
          "date": "2026-07-13"
        },
        {
          "title": "연상호 손끝에서 다시 태어난 日 ‘가스인간’",
          "link": "https://www.donga.com/news/Culture/article/all/20260714/134291815/2",
          "press": "",
          "date": "2026-07-13"
        }
      ],
      "rank": 8
    },
    {
      "keyword": "하나로마트",
      "traffic": "200+",
      "blogTotal": 1414286,
      "newsTotal": 234308,
      "recentToday": 0,
      "recentWeek": 100,
      "topBlogs": [
        {
          "title": "온누리상품권 사용처 하나로마트 사용 및 조회 모바일 검색 방법",
          "link": "https://blog.naver.com/designer_ten/224181358386",
          "blogger": "꼬꼬마 꼬꼬미",
          "date": "2026-02-12"
        },
        {
          "title": "대회 / 하나로마트 사탕뽑기 (with 럭키 쥬시후레쉬 롯데껌)",
          "link": "https://blog.naver.com/charmingfox7/224324347186",
          "blogger": "행복한여우이야기",
          "date": "2026-06-23"
        },
        {
          "title": "수원 키즈카페 추천, 가성비 좋은 서수원 하나로마트 헬로방방",
          "link": "https://blog.naver.com/bikbin/224310218573",
          "blogger": "하루끝 작은기록",
          "date": "2026-06-09"
        },
        {
          "title": "하나로마트 리뉴얼! 캠핑 장보기에도 딱 좋은 봉양 최대 마트",
          "link": "https://blog.naver.com/1004lucia/224337645756",
          "blogger": "천사의 날개짓",
          "date": "2026-07-06"
        },
        {
          "title": "하니원 멜론- 춘천원예농협 (구매처: 춘천농협 하나로마트...",
          "link": "https://blog.naver.com/grenni/224340779717",
          "blogger": "케이비의 City & Food",
          "date": "2026-07-08"
        }
      ],
      "topNews": [
        {
          "title": "병점역 신주거타운 중심 입지… 교통망 확충",
          "link": "https://www.seoul.co.kr/news/economy/estate/2026/07/14/20260714016005?wlog_tag3=naver",
          "press": "",
          "date": "2026-07-13"
        },
        {
          "title": "장마철 골칫거리 참외…‘비건 가죽’ 지갑·가방으로 재탄생",
          "link": "https://www.joongang.co.kr/article/25444790",
          "press": "",
          "date": "2026-07-13"
        },
        {
          "title": "[사진] 초복 식재료 할인판매 합니다",
          "link": "https://www.joongang.co.kr/article/25444756",
          "press": "",
          "date": "2026-07-13"
        },
        {
          "title": "[농협] 인제 두부·진주 쌀 영국 진출 / 하나로마트 누룽지 삼계탕",
          "link": "https://www.webeconomy.co.kr/news/articleView.html?idxno=2231609",
          "press": "",
          "date": "2026-07-13"
        },
        {
          "title": "제주에서 만나는 충북 우수 농산물",
          "link": "https://www.ccdailynews.com/news/articleView.html?idxno=2427829",
          "press": "",
          "date": "2026-07-13"
        }
      ],
      "rank": 9
    },
    {
      "keyword": "기후",
      "traffic": "200+",
      "blogTotal": 4419589,
      "newsTotal": 2829246,
      "recentToday": 0,
      "recentWeek": 100,
      "topBlogs": [
        {
          "title": "기후동행카드 종료…8월 이후엔 K-패스 써야 할까",
          "link": "https://blog.naver.com/rec1820/224343210155",
          "blogger": "JC`Enjoy the Life",
          "date": "2026-07-11"
        },
        {
          "title": "GWP 뜻 지구온난화잠재력이란? 기후동행퀴즈 7월14일 정답",
          "link": "https://blog.naver.com/fine1177/224345696736",
          "blogger": "가가무비의 영화픽",
          "date": "2026-07-14"
        },
        {
          "title": "K-패스 전환 일정, 사라지는 기후동행카드 종료 언제까지?",
          "link": "https://blog.naver.com/dysaghwls/224344294716",
          "blogger": "경제토대왕 부의 전술",
          "date": "2026-07-12"
        },
        {
          "title": "전쟁·관세·기후위기 시대, 이제 투자 공식이 바뀌었다! 새로운...",
          "link": "https://blog.naver.com/eterna01/224344144780",
          "blogger": "Jer 29:11",
          "date": "2026-07-12"
        },
        {
          "title": "\"기후동행카드 9월 종료 실화냐?\" 바뀌는 교통 복지 지도",
          "link": "https://blog.naver.com/alcmskfl17/224343252914",
          "blogger": "피끄의 실험실",
          "date": "2026-07-11"
        }
      ],
      "topNews": [
        {
          "title": "[사설] 메가프로젝트에 재정·인프라 총력 지원, 실행력 높여야",
          "link": "https://www.seoul.co.kr/news/editOpinion/editorial/2026/07/14/20260714027006?wlog_tag3=naver",
          "press": "",
          "date": "2026-07-13"
        },
        {
          "title": "“임기 초 동력 확보”… 지자체장 시정 철학 담은 조직개편 착수",
          "link": "https://www.seoul.co.kr/news/publicnews/local_govern/news_local/2026/07/14/20260714019004?wlog_tag3=naver",
          "press": "",
          "date": "2026-07-13"
        },
        {
          "title": "폭염 탓 ‘초과 사망’…연평균 200명 달해",
          "link": "https://www.seoul.co.kr/news/society/2026/07/14/20260714012005?wlog_tag3=naver",
          "press": "",
          "date": "2026-07-13"
        },
        {
          "title": "[아주초대석] 김성환 기후장관 \"댐 증고 5년 내 가능…반도체 용수·전력...",
          "link": "https://www.ajunews.com/view/20260713091949040",
          "press": "",
          "date": "2026-07-13"
        },
        {
          "title": "[아주초대석] 김성환 기후장관 \"환경·에너지 더는 대립 아냐…'전기국...",
          "link": "https://www.ajunews.com/view/20260713081626876",
          "press": "",
          "date": "2026-07-13"
        }
      ],
      "rank": 10
    }
  ]
}